ictr/__init__.py
ictr/configuration.py
ictr/dispatchers.py
ictr/exceptions.py
ictr/flavors.py
ictr/inspection.py
ictr/printers.py
ictr/py.typed
ictr/records.py
ictr/reporters.py
ictr/textualizers.py
ictr/__/__init__.py
ictr/__/imports.py
ictr/__/miscellany.py
ictr/__/nomina.py
ictr/__/validators.py
ictr/_typedecls/wcwidth/__init__.pyi
ictr/standard/__.py
ictr/standard/__init__.py
ictr/standard/compositors.py
ictr/standard/core.py
ictr/standard/flavors.py
ictr/standard/introducers.py
ictr/standard/linearizers.py
ictr/standard/printers.py
ictr-1.0a0.dist-info/METADATA
ictr-1.0a0.dist-info/WHEEL
ictr-1.0a0.dist-info/licenses/LICENSE.txt
ictr-1.0a0.dist-info/RECORD
