Metadata-Version: 2.4
Name: ictr
Version: 1.0a0
Summary: Non-intrusive system for logging and debug printing.
Project-URL: Homepage, https://github.com/emcd/python-ictr
Project-URL: Documentation, https://emcd.github.io/python-ictr
Project-URL: Download, https://pypi.org/project/ictr/#files
Project-URL: Source Code, https://github.com/emcd/python-ictr
Project-URL: Issue Tracker, https://github.com/emcd/python-ictr/issues
Author-email: Eric McDonald <emcd@users.noreply.github.com>
License-Expression: Apache-2.0
License-File: LICENSE.txt
Keywords: debug,introspection,logging,print
Classifier: Development Status :: 5 - Production/Stable
Classifier: Intended Audience :: Developers
Classifier: License :: OSI Approved :: Apache Software License
Classifier: Programming Language :: Python :: 3 :: Only
Classifier: Programming Language :: Python :: 3.10
Classifier: Programming Language :: Python :: 3.11
Classifier: Programming Language :: Python :: 3.12
Classifier: Programming Language :: Python :: 3.13
Classifier: Programming Language :: Python :: 3.14
Classifier: Programming Language :: Python :: Implementation :: CPython
Classifier: Programming Language :: Python :: Implementation :: PyPy
Classifier: Topic :: Software Development
Requires-Python: >=3.10
Requires-Dist: absence~=1.1
Requires-Dist: accretive~=4.2
Requires-Dist: colorama
Requires-Dist: dynadoc~=1.4
Requires-Dist: exceptiongroup~=1.3
Requires-Dist: frigid~=4.2
Requires-Dist: typing-extensions~=4.15
Requires-Dist: wcwidth~=0.2.14
Provides-Extra: deluxe
Requires-Dist: rich~=14.2; extra == 'deluxe'
